Spruce_exc-0.1.0-py2.7-nspkg.pth
spruce/exc/_exc.py
spruce/exc/__init__.py
Spruce_exc-0.1.0.dist-info/METADATA
Spruce_exc-0.1.0.dist-info/entry_points.txt
Spruce_exc-0.1.0.dist-info/RECORD
Spruce_exc-0.1.0.dist-info/top_level.txt
Spruce_exc-0.1.0.dist-info/namespace_packages.txt
Spruce_exc-0.1.0.dist-info/WHEEL
Spruce_exc-0.1.0.dist-info/metadata.json
Spruce_exc-0.1.0.dist-info/DESCRIPTION.rst
