Metadata-Version: 2.0
Name: Spruce-exc
Version: 0.1.0
Summary: Exceptions
Home-page: UNKNOWN
Author: Ivan D Vasin
Author-email: nisavid@gmail.com
License: GNU LESSER GENERAL PUBLIC LICENSE
